archlens_preview-0.1.2.data/data/config.schema.json
archlens_preview-0.1.2.data/data/config.template.json
src/__init__.py
src/cli_interface.py
src/config.schema.json
src/config.template.json
src/main.py
src/core/__init__.py
src/core/bt_file.py
src/core/bt_graph.py
src/core/bt_module.py
src/plantuml/__init__.py
src/plantuml/fetch_git.py
src/plantuml/plantuml_file_creator.py
src/plantumlv2/__init__.py
src/plantumlv2/pu_entities.py
src/plantumlv2/pu_manager.py
src/plantumlv2/utils.py
src/utils/__init__.py
src/utils/config_manager_singleton.py
src/utils/functions.py
src/utils/path_manager_singleton.py
archlens_preview-0.1.2.dist-info/METADATA
archlens_preview-0.1.2.dist-info/WHEEL
archlens_preview-0.1.2.dist-info/entry_points.txt
archlens_preview-0.1.2.dist-info/top_level.txt
archlens_preview-0.1.2.dist-info/RECORD
